LICENSE
MANIFEST.in
README.rst
setup.py
data_masker/__init__.py
data_masker/admin.py
data_masker/apps.py
data_masker/models.py
data_masker/tests.py
data_masker/views.py
data_masker/migrations/__init__.py
data_masker/templatetags/data_masker.py
django_data_masker.egg-info/PKG-INFO
django_data_masker.egg-info/SOURCES.txt
django_data_masker.egg-info/dependency_links.txt
django_data_masker.egg-info/top_level.txt